flask_edfapay/__init__.py
flask_edfapay/edfapay.py
flask_edfapay-0.1.dist-info/LICENSE
flask_edfapay-0.1.dist-info/METADATA
flask_edfapay-0.1.dist-info/WHEEL
flask_edfapay-0.1.dist-info/top_level.txt
flask_edfapay-0.1.dist-info/RECORD
